mongodbtools/__init__.py
mongodbtools/cursor_reader.py
mongodbtools/entry_points.py
mongodbtools/etl_utils.py
mongodbtools/exceptions.py
mongodbtools/mongoconnection.py
mongodbtools/resources.py
mongodbtools/config/mongo.cfg
mongodbtools/links/__init__.py
mongodbtools/links/check_collection.py
mongodbtools/links/collection_to_df.py
mongodbtools/links/cursor_to_df.py
mongodbtools/links/data_to_collection.py
mongodbtools/links/delete_many_from_df.py
mongodbtools/links/df_to_collection.py
mongodbtools/links/df_to_idfilter.py
mongodbtools/links/doc_to_collection.py
mongodbtools/links/empty_collection.py
mongodbtools/links/merge_labels.py
mongodbtools/links/mongocheckcollection.py
mongodbtools/links/mongocollectiontodf.py
mongodbtools/links/mongocursor2df.py
mongodbtools/links/mongodatatocollection.py
mongodbtools/links/mongodeletemanyfromdf.py
mongodbtools/links/mongodf_to_idfilter.py
mongodbtools/links/mongodftocollection.py
mongodbtools/links/mongoemptycollection.py
mongodbtools/links/mongomergelabels.py
mongodbtools/links/mongomovecollection.py
mongodbtools/links/mongooverview.py
mongodbtools/links/move_collection.py
mongodbtools/links/overview.py
mongodbtools/links/retrieve_last_added.py
mongodbtools/links/skip_chain_if_collection_empty.py
MongoDBTools-0.1.1.dist-info/METADATA
MongoDBTools-0.1.1.dist-info/WHEEL
MongoDBTools-0.1.1.dist-info/entry_points.txt
MongoDBTools-0.1.1.dist-info/top_level.txt
MongoDBTools-0.1.1.dist-info/RECORD
